watson/__init__.py
watson/html/__init__.py
watson/html/elements.py
watson/html/entities.py
watson_html-1.2.1.dist-info/AUTHORS
watson_html-1.2.1.dist-info/LICENSE
watson_html-1.2.1.dist-info/METADATA
watson_html-1.2.1.dist-info/WHEEL
watson_html-1.2.1.dist-info/top_level.txt
watson_html-1.2.1.dist-info/RECORD
