Metadata-Version: 2.1
Name: watson-html
Version: 1.2.1
Summary: Utility methods for dealing with HTML.
Home-page: http://github.com/watsonpy/watson-html
Author: Simon Coulton
Author-email: simon@bespohk.com
License: Copyright (c) Bespohk and individual contributors.
Requires-Dist: watson-common (>=1.3.0)
Provides-Extra: test
Requires-Dist: pytest ; extra == 'test'
Requires-Dist: pytest-cov ; extra == 'test'
Requires-Dist: coverage ; extra == 'test'
Requires-Dist: coveralls ; extra == 'test'
